backend/__init__.py
backend/quantum_simulation.py
quantum_ai/__init__.py
quantum_finance/__init__.py
quantum_finance/advanced_meta_update.py
quantum_finance/ai_prediction.py
quantum_finance/ai_predictor.py
quantum_finance/app.py
quantum_finance/benchmarks.py
quantum_finance/data_sources.py
quantum_finance/dynamic_circuit.py
quantum_finance/dynamic_circuit_refactoring_optimized.py
quantum_finance/ibm_quantum_enhanced.py
quantum_finance/ibm_quantum_integration.py
quantum_finance/ibm_quantum_integration_fixed.py
quantum_finance/ibm_quantum_usage_report.py
quantum_finance/integrated_meta_optimizer.py
quantum_finance/integration_flow.py
quantum_finance/main.py
quantum_finance/meta_learning.py
quantum_finance/meta_optimizer.py
quantum_finance/qio_module.py
quantum_finance/quantum_ai_interface.py
quantum_finance/quantum_ai_model.py
quantum_finance/quantum_ai_model_fixed.py
quantum_finance/quantum_ai_pipeline.py
quantum_finance/quantum_ai_utils.py
quantum_finance/quantum_bayesian_risk.py
quantum_finance/quantum_benchmark.py
quantum_finance/quantum_enhanced_crypto_risk.py
quantum_finance/quantum_enhanced_crypto_risk_wrapper.py
quantum_finance/quantum_financial_benchmark.py
quantum_finance/quantum_financial_benchmark_risk.py
quantum_finance/quantum_market_encoding.py
quantum_finance/quantum_performance_test.py
quantum_finance/quantum_sim.py
quantum_finance/quantum_simulation.py
quantum_finance/quantum_visualization.py
quantum_finance/real_time_risk_monitor.py
quantum_finance/run_realtime_risk_demo.py
quantum_finance/simulation_experiment.py
quantum_finance/unified_data_pipeline.py
quantum_finance/w_state_theory_analysis.py
quantum_finance/api/__init__.py
quantum_finance/api/quantum_financial_api.py
quantum_finance/api/config/__init__.py
quantum_finance/api/core/__init__.py
quantum_finance/api/core/cache_manager.py
quantum_finance/api/core/coincap_analyzer.py
quantum_finance/api/core/coindesk_analyzer.py
quantum_finance/api/core/comparator.py
quantum_finance-0.2.0.dist-info/METADATA
quantum_finance-0.2.0.dist-info/WHEEL
quantum_finance-0.2.0.dist-info/entry_points.txt
quantum_finance-0.2.0.dist-info/top_level.txt
quantum_finance-0.2.0.dist-info/RECORD
